vocos_mlx/__init__.py
vocos_mlx/audio.py
vocos_mlx/encodec.py
vocos_mlx/mel.py
vocos_mlx/model.py
vocos_mlx-0.0.7.dist-info/LICENSE
vocos_mlx-0.0.7.dist-info/METADATA
vocos_mlx-0.0.7.dist-info/WHEEL
vocos_mlx-0.0.7.dist-info/top_level.txt
vocos_mlx-0.0.7.dist-info/RECORD
